trytry/__init__.py
trytry-0.1.2.dist-info/WHEEL
trytry-0.1.2.dist-info/METADATA
trytry-0.1.2.dist-info/RECORD
